{".class":"MypyFile","_fullname":"matchpredictor.upcominggames.football_data_api_client","future_import_flags":[],"is_partial_stub_package":false,"is_stub":false,"names":{".class":"SymbolTable","FootballDataApiClient":{".class":"SymbolTableNode","kind":"Gdef","node":{".class":"TypeInfo","_promote":[],"abstract_attributes":[],"alt_promote":null,"bases":["builtins.object"],"dataclass_transform_spec":null,"declared_metaclass":null,"defn":{".class":"ClassDef","fullname":"matchpredictor.upcominggames.football_data_api_client.FootballDataApiClient","name":"FootballDataApiClient","type_vars":[]},"deletable_attributes":[],"flags":[],"fullname":"matchpredictor.upcominggames.football_data_api_client.FootballDataApiClient","has_param_spec_type":false,"metaclass_type":null,"metadata":{},"module_name":"matchpredictor.upcominggames.football_data_api_client","mro":["matchpredictor.upcominggames.football_data_api_client.FootballDataApiClient","builtins.object"],"names":{".class":"SymbolTable","__init__":{".class":"SymbolTableNode","kind":"Mdef","node":{".class":"FuncDef","abstract_status":0,"arg_kinds":[0,0],"arg_names":["self","api_key"],"dataclass_transform_spec":null,"flags":[],"fullname":"matchpredictor.upcominggames.football_data_api_client.FootballDataApiClient.__init__","name":"__init__","type":{".class":"CallableType","arg_kinds":[0,0],"arg_names":["self","api_key"],"arg_types":["matchpredictor.upcominggames.football_data_api_client.FootballDataApiClient","builtins.str"],"bound_args":[],"def_extras":{"first_arg":"self"},"fallback":"builtins.function","from_concatenate":false,"implicit":false,"is_ellipsis_args":false,"name":"__init__ of FootballDataApiClient","ret_type":{".class":"NoneType"},"type_guard":null,"unpack_kwargs":false,"variables":[]}}},"api_key":{".class":"SymbolTableNode","implicit":true,"kind":"Mdef","node":{".class":"Var","flags":["is_inferred"],"fullname":"matchpredictor.upcominggames.football_data_api_client.FootballDataApiClient.api_key","name":"api_key","type":"builtins.str"}},"fetch_matches":{".class":"SymbolTableNode","kind":"Mdef","node":{".class":"FuncDef","abstract_status":0,"arg_kinds":[0,0],"arg_names":["self","date_from"],"dataclass_transform_spec":null,"flags":[],"fullname":"matchpredictor.upcominggames.football_data_api_client.FootballDataApiClient.fetch_matches","name":"fetch_matches","type":{".class":"CallableType","arg_kinds":[0,0],"arg_names":["self","date_from"],"arg_types":["matchpredictor.upcominggames.football_data_api_client.FootballDataApiClient","datetime.date"],"bound_args":[],"def_extras":{"first_arg":"self"},"fallback":"builtins.function","from_concatenate":false,"implicit":false,"is_ellipsis_args":false,"name":"fetch_matches of FootballDataApiClient","ret_type":{".class":"UnionType","items":["matchpredictor.upcominggames.football_data_api_client.FootballDataMatchesResponse",{".class":"NoneType"}]},"type_guard":null,"unpack_kwargs":false,"variables":[]}}},"nine_days":{".class":"SymbolTableNode","kind":"Mdef","node":{".class":"Var","flags":["is_initialized_in_class","is_inferred","has_explicit_value"],"fullname":"matchpredictor.upcominggames.football_data_api_client.FootballDataApiClient.nine_days","name":"nine_days","type":"datetime.timedelta"}}},"self_type":null,"slots":null,"tuple_type":null,"type_vars":[],"typeddict_type":null}},"FootballDataMatchesResponse":{".class":"SymbolTableNode","kind":"Gdef","node":{".class":"TypeInfo","_promote":[],"abstract_attributes":[],"alt_promote":null,"bases":["builtins.object"],"dataclass_transform_spec":null,"declared_metaclass":null,"defn":{".class":"ClassDef","fullname":"matchpredictor.upcominggames.football_data_api_client.FootballDataMatchesResponse","name":"FootballDataMatchesResponse","type_vars":[]},"deletable_attributes":[],"flags":[],"fullname":"matchpredictor.upcominggames.football_data_api_client.FootballDataMatchesResponse","has_param_spec_type":false,"metaclass_type":null,"metadata":{"dataclass":{"attributes":[{"alias":null,"column":4,"has_default":false,"is_in_init":true,"is_init_var":false,"is_neither_frozen_nor_nonfrozen":false,"kw_only":false,"line":30,"name":"matches","type":{".class":"Instance","args":["matchpredictor.upcominggames.football_data_api_client.MatchJson"],"type_ref":"builtins.list"}}],"frozen":true},"dataclass_tag":{}},"module_name":"matchpredictor.upcominggames.football_data_api_client","mro":["matchpredictor.upcominggames.football_data_api_client.FootballDataMatchesResponse","builtins.object"],"names":{".class":"SymbolTable","__dataclass_fields__":{".class":"SymbolTableNode","kind":"Mdef","node":{".class":"Var","flags":["is_classvar","is_ready"],"fullname":"matchpredictor.upcominggames.football_data_api_client.FootballDataMatchesResponse.__dataclass_fields__","name":"__dataclass_fields__","type":{".class":"Instance","args":["builtins.str",{".class":"Instance","args":[{".class":"AnyType","missing_import_name":null,"source_any":null,"type_of_any":2}],"type_ref":"dataclasses.Field"}],"type_ref":"builtins.dict"}},"plugin_generated":true},"__init__":{".class":"SymbolTableNode","kind":"Mdef","node":{".class":"FuncDef","abstract_status":0,"arg_kinds":[0,0],"arg_names":["self","matches"],"dataclass_transform_spec":null,"flags":[],"fullname":"matchpredictor.upcominggames.football_data_api_client.FootballDataMatchesResponse.__init__","name":"__init__","type":{".class":"CallableType","arg_kinds":[0,0],"arg_names":["self","matches"],"arg_types":["matchpredictor.upcominggames.football_data_api_client.FootballDataMatchesResponse",{".class":"Instance","args":["matchpredictor.upcominggames.football_data_api_client.MatchJson"],"type_ref":"builtins.list"}],"bound_args":[],"def_extras":{},"fallback":"builtins.function","from_concatenate":false,"implicit":false,"is_ellipsis_args":false,"name":"__init__ of FootballDataMatchesResponse","ret_type":{".class":"NoneType"},"type_guard":null,"unpack_kwargs":false,"variables":[]}},"plugin_generated":true},"__match_args__":{".class":"SymbolTableNode","kind":"Mdef","node":{".class":"Var","flags":["is_ready","allow_incompatible_override"],"fullname":"matchpredictor.upcominggames.football_data_api_client.FootballDataMatchesResponse.__match_args__","name":"__match_args__","type":{".class":"TupleType","implicit":false,"items":[{".class":"LiteralType","fallback":"builtins.str","value":"matches"}],"partial_fallback":{".class":"Instance","args":[{".class":"AnyType","missing_import_name":null,"source_any":null,"type_of_any":6}],"type_ref":"builtins.tuple"}}},"plugin_generated":true},"matches":{".class":"SymbolTableNode","implicit":true,"kind":"Mdef","node":{".class":"Var","flags":["is_initialized_in_class","is_property","is_ready"],"fullname":"matchpredictor.upcominggames.football_data_api_client.FootballDataMatchesResponse.matches","name":"matches","type":{".class":"Instance","args":["matchpredictor.upcominggames.football_data_api_client.MatchJson"],"type_ref":"builtins.list"}}}},"self_type":null,"slots":null,"tuple_type":null,"type_vars":[],"typeddict_type":null}},"MatchJson":{".class":"SymbolTableNode","kind":"Gdef","node":{".class":"TypeInfo","_promote":[],"abstract_attributes":[],"alt_promote":null,"bases":["builtins.object"],"dataclass_transform_spec":null,"declared_metaclass":null,"defn":{".class":"ClassDef","fullname":"matchpredictor.upcominggames.football_data_api_client.MatchJson","name":"MatchJson","type_vars":[]},"deletable_attributes":[],"flags":[],"fullname":"matchpredictor.upcominggames.football_data_api_client.MatchJson","has_param_spec_type":false,"metaclass_type":null,"metadata":{"dataclass":{"attributes":[{"alias":null,"column":4,"has_default":false,"is_in_init":true,"is_init_var":false,"is_neither_frozen_nor_nonfrozen":false,"kw_only":false,"line":22,"name":"area","type":"matchpredictor.upcominggames.football_data_api_client.NamedJson"},{"alias":null,"column":4,"has_default":false,"is_in_init":true,"is_init_var":false,"is_neither_frozen_nor_nonfrozen":false,"kw_only":false,"line":23,"name":"competition","type":"matchpredictor.upcominggames.football_data_api_client.NamedJson"},{"alias":null,"column":4,"has_default":false,"is_in_init":true,"is_init_var":false,"is_neither_frozen_nor_nonfrozen":false,"kw_only":false,"line":24,"name":"homeTeam","type":"matchpredictor.upcominggames.football_data_api_client.TeamJson"},{"alias":null,"column":4,"has_default":false,"is_in_init":true,"is_init_var":false,"is_neither_frozen_nor_nonfrozen":false,"kw_only":false,"line":25,"name":"awayTeam","type":"matchpredictor.upcominggames.football_data_api_client.TeamJson"}],"frozen":true},"dataclass_tag":{}},"module_name":"matchpredictor.upcominggames.football_data_api_client","mro":["matchpredictor.upcominggames.football_data_api_client.MatchJson","builtins.object"],"names":{".class":"SymbolTable","__dataclass_fields__":{".class":"SymbolTableNode","kind":"Mdef","node":{".class":"Var","flags":["is_classvar","is_ready"],"fullname":"matchpredictor.upcominggames.football_data_api_client.MatchJson.__dataclass_fields__","name":"__dataclass_fields__","type":{".class":"Instance","args":["builtins.str",{".class":"Instance","args":[{".class":"AnyType","missing_import_name":null,"source_any":null,"type_of_any":2}],"type_ref":"dataclasses.Field"}],"type_ref":"builtins.dict"}},"plugin_generated":true},"__init__":{".class":"SymbolTableNode","kind":"Mdef","node":{".class":"FuncDef","abstract_status":0,"arg_kinds":[0,0,0,0,0],"arg_names":["self","area","competition","homeTeam","awayTeam"],"dataclass_transform_spec":null,"flags":[],"fullname":"matchpredictor.upcominggames.football_data_api_client.MatchJson.__init__","name":"__init__","type":{".class":"CallableType","arg_kinds":[0,0,0,0,0],"arg_names":["self","area","competition","homeTeam","awayTeam"],"arg_types":["matchpredictor.upcominggames.football_data_api_client.MatchJson","matchpredictor.upcominggames.football_data_api_client.NamedJson","matchpredictor.upcominggames.football_data_api_client.NamedJson","matchpredictor.upcominggames.football_data_api_client.TeamJson","matchpredictor.upcominggames.football_data_api_client.TeamJson"],"bound_args":[],"def_extras":{},"fallback":"builtins.function","from_concatenate":false,"implicit":false,"is_ellipsis_args":false,"name":"__init__ of MatchJson","ret_type":{".class":"NoneType"},"type_guard":null,"unpack_kwargs":false,"variables":[]}},"plugin_generated":true},"__match_args__":{".class":"SymbolTableNode","kind":"Mdef","node":{".class":"Var","flags":["is_ready","allow_incompatible_override"],"fullname":"matchpredictor.upcominggames.football_data_api_client.MatchJson.__match_args__","name":"__match_args__","type":{".class":"TupleType","implicit":false,"items":[{".class":"LiteralType","fallback":"builtins.str","value":"area"},{".class":"LiteralType","fallback":"builtins.str","value":"competition"},{".class":"LiteralType","fallback":"builtins.str","value":"homeTeam"},{".class":"LiteralType","fallback":"builtins.str","value":"awayTeam"}],"partial_fallback":{".class":"Instance","args":[{".class":"AnyType","missing_import_name":null,"source_any":null,"type_of_any":6}],"type_ref":"builtins.tuple"}}},"plugin_generated":true},"area":{".class":"SymbolTableNode","implicit":true,"kind":"Mdef","node":{".class":"Var","flags":["is_initialized_in_class","is_property","is_ready"],"fullname":"matchpredictor.upcominggames.football_data_api_client.MatchJson.area","name":"area","type":"matchpredictor.upcominggames.football_data_api_client.NamedJson"}},"awayTeam":{".class":"SymbolTableNode","implicit":true,"kind":"Mdef","node":{".class":"Var","flags":["is_initialized_in_class","is_property","is_ready"],"fullname":"matchpredictor.upcominggames.football_data_api_client.MatchJson.awayTeam","name":"awayTeam","type":"matchpredictor.upcominggames.football_data_api_client.TeamJson"}},"competition":{".class":"SymbolTableNode","implicit":true,"kind":"Mdef","node":{".class":"Var","flags":["is_initialized_in_class","is_property","is_ready"],"fullname":"matchpredictor.upcominggames.football_data_api_client.MatchJson.competition","name":"competition","type":"matchpredictor.upcominggames.football_data_api_client.NamedJson"}},"homeTeam":{".class":"SymbolTableNode","implicit":true,"kind":"Mdef","node":{".class":"Var","flags":["is_initialized_in_class","is_property","is_ready"],"fullname":"matchpredictor.upcominggames.football_data_api_client.MatchJson.homeTeam","name":"homeTeam","type":"matchpredictor.upcominggames.football_data_api_client.TeamJson"}}},"self_type":null,"slots":null,"tuple_type":null,"type_vars":[],"typeddict_type":null}},"NamedJson":{".class":"SymbolTableNode","kind":"Gdef","node":{".class":"TypeInfo","_promote":[],"abstract_attributes":[],"alt_promote":null,"bases":["builtins.object"],"dataclass_transform_spec":null,"declared_metaclass":null,"defn":{".class":"ClassDef","fullname":"matchpredictor.upcominggames.football_data_api_client.NamedJson","name":"NamedJson","type_vars":[]},"deletable_attributes":[],"flags":[],"fullname":"matchpredictor.upcominggames.football_data_api_client.NamedJson","has_param_spec_type":false,"metaclass_type":null,"metadata":{"dataclass":{"attributes":[{"alias":null,"column":4,"has_default":false,"is_in_init":true,"is_init_var":false,"is_neither_frozen_nor_nonfrozen":false,"kw_only":false,"line":12,"name":"name","type":"builtins.str"}],"frozen":true},"dataclass_tag":{}},"module_name":"matchpredictor.upcominggames.football_data_api_client","mro":["matchpredictor.upcominggames.football_data_api_client.NamedJson","builtins.object"],"names":{".class":"SymbolTable","__dataclass_fields__":{".class":"SymbolTableNode","kind":"Mdef","node":{".class":"Var","flags":["is_classvar","is_ready"],"fullname":"matchpredictor.upcominggames.football_data_api_client.NamedJson.__dataclass_fields__","name":"__dataclass_fields__","type":{".class":"Instance","args":["builtins.str",{".class":"Instance","args":[{".class":"AnyType","missing_import_name":null,"source_any":null,"type_of_any":2}],"type_ref":"dataclasses.Field"}],"type_ref":"builtins.dict"}},"plugin_generated":true},"__init__":{".class":"SymbolTableNode","kind":"Mdef","node":{".class":"FuncDef","abstract_status":0,"arg_kinds":[0,0],"arg_names":["self","name"],"dataclass_transform_spec":null,"flags":[],"fullname":"matchpredictor.upcominggames.football_data_api_client.NamedJson.__init__","name":"__init__","type":{".class":"CallableType","arg_kinds":[0,0],"arg_names":["self","name"],"arg_types":["matchpredictor.upcominggames.football_data_api_client.NamedJson","builtins.str"],"bound_args":[],"def_extras":{},"fallback":"builtins.function","from_concatenate":false,"implicit":false,"is_ellipsis_args":false,"name":"__init__ of NamedJson","ret_type":{".class":"NoneType"},"type_guard":null,"unpack_kwargs":false,"variables":[]}},"plugin_generated":true},"__match_args__":{".class":"SymbolTableNode","kind":"Mdef","node":{".class":"Var","flags":["is_ready","allow_incompatible_override"],"fullname":"matchpredictor.upcominggames.football_data_api_client.NamedJson.__match_args__","name":"__match_args__","type":{".class":"TupleType","implicit":false,"items":[{".class":"LiteralType","fallback":"builtins.str","value":"name"}],"partial_fallback":{".class":"Instance","args":[{".class":"AnyType","missing_import_name":null,"source_any":null,"type_of_any":6}],"type_ref":"builtins.tuple"}}},"plugin_generated":true},"name":{".class":"SymbolTableNode","implicit":true,"kind":"Mdef","node":{".class":"Var","flags":["is_initialized_in_class","is_property","is_ready"],"fullname":"matchpredictor.upcominggames.football_data_api_client.NamedJson.name","name":"name","type":"builtins.str"}}},"self_type":null,"slots":null,"tuple_type":null,"type_vars":[],"typeddict_type":null}},"Optional":{".class":"SymbolTableNode","cross_ref":"typing.Optional","kind":"Gdef","module_hidden":true,"module_public":false},"TeamJson":{".class":"SymbolTableNode","kind":"Gdef","node":{".class":"TypeInfo","_promote":[],"abstract_attributes":[],"alt_promote":null,"bases":["builtins.object"],"dataclass_transform_spec":null,"declared_metaclass":null,"defn":{".class":"ClassDef","fullname":"matchpredictor.upcominggames.football_data_api_client.TeamJson","name":"TeamJson","type_vars":[]},"deletable_attributes":[],"flags":[],"fullname":"matchpredictor.upcominggames.football_data_api_client.TeamJson","has_param_spec_type":false,"metaclass_type":null,"metadata":{"dataclass":{"attributes":[{"alias":null,"column":4,"has_default":false,"is_in_init":true,"is_init_var":false,"is_neither_frozen_nor_nonfrozen":false,"kw_only":false,"line":17,"name":"shortName","type":"builtins.str"}],"frozen":true},"dataclass_tag":{}},"module_name":"matchpredictor.upcominggames.football_data_api_client","mro":["matchpredictor.upcominggames.football_data_api_client.TeamJson","builtins.object"],"names":{".class":"SymbolTable","__dataclass_fields__":{".class":"SymbolTableNode","kind":"Mdef","node":{".class":"Var","flags":["is_classvar","is_ready"],"fullname":"matchpredictor.upcominggames.football_data_api_client.TeamJson.__dataclass_fields__","name":"__dataclass_fields__","type":{".class":"Instance","args":["builtins.str",{".class":"Instance","args":[{".class":"AnyType","missing_import_name":null,"source_any":null,"type_of_any":2}],"type_ref":"dataclasses.Field"}],"type_ref":"builtins.dict"}},"plugin_generated":true},"__init__":{".class":"SymbolTableNode","kind":"Mdef","node":{".class":"FuncDef","abstract_status":0,"arg_kinds":[0,0],"arg_names":["self","shortName"],"dataclass_transform_spec":null,"flags":[],"fullname":"matchpredictor.upcominggames.football_data_api_client.TeamJson.__init__","name":"__init__","type":{".class":"CallableType","arg_kinds":[0,0],"arg_names":["self","shortName"],"arg_types":["matchpredictor.upcominggames.football_data_api_client.TeamJson","builtins.str"],"bound_args":[],"def_extras":{},"fallback":"builtins.function","from_concatenate":false,"implicit":false,"is_ellipsis_args":false,"name":"__init__ of TeamJson","ret_type":{".class":"NoneType"},"type_guard":null,"unpack_kwargs":false,"variables":[]}},"plugin_generated":true},"__match_args__":{".class":"SymbolTableNode","kind":"Mdef","node":{".class":"Var","flags":["is_ready","allow_incompatible_override"],"fullname":"matchpredictor.upcominggames.football_data_api_client.TeamJson.__match_args__","name":"__match_args__","type":{".class":"TupleType","implicit":false,"items":[{".class":"LiteralType","fallback":"builtins.str","value":"shortName"}],"partial_fallback":{".class":"Instance","args":[{".class":"AnyType","missing_import_name":null,"source_any":null,"type_of_any":6}],"type_ref":"builtins.tuple"}}},"plugin_generated":true},"shortName":{".class":"SymbolTableNode","implicit":true,"kind":"Mdef","node":{".class":"Var","flags":["is_initialized_in_class","is_property","is_ready"],"fullname":"matchpredictor.upcominggames.football_data_api_client.TeamJson.shortName","name":"shortName","type":"builtins.str"}}},"self_type":null,"slots":null,"tuple_type":null,"type_vars":[],"typeddict_type":null}},"__annotations__":{".class":"SymbolTableNode","kind":"Gdef","node":{".class":"Var","flags":["is_ready"],"fullname":"matchpredictor.upcominggames.football_data_api_client.__annotations__","name":"__annotations__","type":{".class":"Instance","args":["builtins.str",{".class":"AnyType","missing_import_name":null,"source_any":null,"type_of_any":6}],"type_ref":"builtins.dict"}}},"__doc__":{".class":"SymbolTableNode","kind":"Gdef","node":{".class":"Var","flags":["is_ready"],"fullname":"matchpredictor.upcominggames.football_data_api_client.__doc__","name":"__doc__","type":"builtins.str"}},"__file__":{".class":"SymbolTableNode","kind":"Gdef","node":{".class":"Var","flags":["is_ready"],"fullname":"matchpredictor.upcominggames.football_data_api_client.__file__","name":"__file__","type":"builtins.str"}},"__name__":{".class":"SymbolTableNode","kind":"Gdef","node":{".class":"Var","flags":["is_ready"],"fullname":"matchpredictor.upcominggames.football_data_api_client.__name__","name":"__name__","type":"builtins.str"}},"__package__":{".class":"SymbolTableNode","kind":"Gdef","node":{".class":"Var","flags":["is_ready"],"fullname":"matchpredictor.upcominggames.football_data_api_client.__package__","name":"__package__","type":"builtins.str"}},"dacite":{".class":"SymbolTableNode","cross_ref":"dacite","kind":"Gdef","module_hidden":true,"module_public":false},"dataclass":{".class":"SymbolTableNode","cross_ref":"dataclasses.dataclass","kind":"Gdef","module_hidden":true,"module_public":false},"date":{".class":"SymbolTableNode","cross_ref":"datetime.date","kind":"Gdef","module_hidden":true,"module_public":false},"datetime":{".class":"SymbolTableNode","cross_ref":"datetime","kind":"Gdef","module_hidden":true,"module_public":false},"requests":{".class":"SymbolTableNode","cross_ref":"requests","kind":"Gdef","module_hidden":true,"module_public":false}},"path":"matchpredictor/upcominggames/football_data_api_client.py"}